{"Search":[{"Title":"The Lego Movie","Year":"2014","imdbID":"tt1490017","Type":"movie","Poster":"https:\/\/m.media-amazon.com\/images\/M\/MV5BMTg4MDk1ODExN15BMl5BanBnXkFtZTgwNzIyNjg3MDE@._V1_SX300.jpg"},{"Title":"The LEGO Batman Movie","Year":"2017","imdbID":"tt4116284","Type":"movie","Poster":"https:\/\/ia.media-imdb.com\/images\/M\/MV5BMTcyNTEyOTY0M15BMl5BanBnXkFtZTgwOTAyNzU3MDI@._V1_SX300.jpg"},{"Title":"The Lego Ninjago Movie","Year":"2017","imdbID":"tt3014284","Type":"movie","Poster":"https:\/\/ia.media-imdb.com\/images\/M\/MV5BNDI3MDljMTQtYzBiYS00NDk2LTlhYzUtYmM0NWIyMmZkMDZkXkEyXkFqcGdeQXVyNjk5NDA3OTk@._V1_SX300.jpg"},{"Title":"Lego Batman: The Movie - DC Super Heroes Unite","Year":"2013","imdbID":"tt2465238","Type":"movie","Poster":"https:\/\/ia.media-imdb.com\/images\/M\/MV5BMjE4MTU5MDk5OF5BMl5BanBnXkFtZTgwNDQ1NzA2MDE@._V1_SX300.jpg"},{"Title":"Lego Marvel Super Heroes","Year":"2013","imdbID":"tt2620204","Type":"game","Poster":"https:\/\/ia.media-imdb.com\/images\/M\/MV5BOTA5ODA2NTI2M15BMl5BanBnXkFtZTgwNTcxMzU1MDE@._V1_SX300.jpg"},{"Title":"Lego Batman: The Videogame","Year":"2008","imdbID":"tt1149317","Type":"game","Poster":"https:\/\/images-na.ssl-images-amazon.com\/images\/M\/MV5BMTI5MjA2MjY4MF5BMl5BanBnXkFtZTcwNzgyOTc3MQ@@._V1_SX300.jpg"},{"Title":"A Lego Brickumentary","Year":"2014","imdbID":"tt3214286","Type":"movie","Poster":"https:\/\/ia.media-imdb.com\/images\/M\/MV5BMTA5Njk2MTQ1NjBeQTJeQWpwZ15BbWU4MDM2MDA0NjUx._V1_SX300.jpg"},{"Title":"Lego Star Wars: The Complete Saga","Year":"2007","imdbID":"tt1149396","Type":"game","Poster":"https:\/\/images-na.ssl-images-amazon.com\/images\/M\/MV5BYjE5YmNiMTItOTAzZi00ZjlmLWE4YzUtZmY2MGFlMzY1ZDMyXkEyXkFqcGdeQXVyNDQ2OTk4MzI@._V1_SX300.jpg"},{"Title":"Lego: The Adventures of Clutch Powers","Year":"2010","imdbID":"tt1587414","Type":"movie","Poster":"https:\/\/ia.media-imdb.com\/images\/M\/MV5BMjQ1NzM2MDE2Nl5BMl5BanBnXkFtZTcwNjg4NDcxMw@@._V1_SX300.jpg"},{"Title":"Lego DC Comics Super Heroes: Justice League vs. Bizarro League","Year":"2015","imdbID":"tt4189260","Type":"movie","Poster":"https:\/\/images-na.ssl-images-amazon.com\/images\/M\/MV5BMjIzMTYxMjk5MV5BMl5BanBnXkFtZTgwMjY5OTgyNDE@._V1_SX300.jpg"}],"totalResults":"194","Response":"True"}